shelmet/__init__.py
shelmet/archiving.py
shelmet/command.py
shelmet/fileio.py
shelmet/filesystem.py
shelmet/path.py
shelmet/types.py
shelmet-0.6.0.dist-info/AUTHORS.rst
shelmet-0.6.0.dist-info/LICENSE.rst
shelmet-0.6.0.dist-info/METADATA
shelmet-0.6.0.dist-info/WHEEL
shelmet-0.6.0.dist-info/top_level.txt
shelmet-0.6.0.dist-info/RECORD
